{
    "dependencies": {
        "particles": [],
        "models": [
            {
                "path": "data/hd/items/weapon/sword/hexfire/hexfire.model"
            }
        ],
        "skeletons": [
            {
                "path": "data/hd/items/weapon/sword/hexfire/skeleton/hexfire.skeleton"
            }
        ],
        "animations": [],
        "textures": [
            {
                "path": "data/hd/items/weapon/sword/hexfire/weapon_hexfire_ALB.texture"
            },
            {
                "path": "data/hd/items/weapon/sword/hexfire/weapon_hexfire_mask.texture"
            },
            {
                "path": "data/hd/items/weapon/sword/hexfire/weapon_hexfire_NRM.texture"
            },
            {
                "path": "data/hd/items/weapon/sword/hexfire/weapon_hexfire_ORM.texture"
            }
        ],
        "physics": [],
        "json": [
            {
                "path": "data/hd/items/dropped_items/dropped_items_sw_left.json"
            }
        ],
        "variantdata": [],
        "objecteffects": [],
        "other": []
    },
    "type": "UnitDefinition",
    "name": "hexfire",
    "entities": [
        {
            "type": "Entity",
            "name": "entity_root",
            "id": 1616892728,
            "components": [
                {
                    "type": "UnitRootComponent",
                    "name": "component_root",
                    "state_machine_filename": "data/hd/items/dropped_items/dropped_items_sw_left.json",
                    "doNotInheritRotation": false,
                    "rotationOverride": {
                        "x": 0.0,
                        "y": 0.3826834,
                        "z": 0.0,
                        "w": 0.9238795
                    },
                    "doNotUseHDHeight": false,
                    "hideAllMeshWhenInOpenedMode": false,
                    "onCreateEventName": "",
                    "animations": []
                },
                {
                    "type": "SkeletonDefinitionComponent",
                    "name": "component_skeleton",
                    "filename": "data/hd/items/weapon/sword/hexfire/skeleton/hexfire.skeleton"
                },
                {
                    "type": "TransformDefinitionComponent",
                    "name": "entity_root_TransformDefinition",
                    "position": {
                        "x": 0.0,
                        "y": 0.0,
                        "z": 0.0
                    },
                    "orientation": {
                        "x": 0.0,
                        "y": -0.06975647,
                        "z": 0.0,
                        "w": 0.9975641
                    },
                    "scale": {
                        "x": 1.2,
                        "y": 1.2,
                        "z": 1.2
                    },
                    "inheritOnlyPosition": false
                }
            ]
        },
        {
            "type": "Entity",
            "name": "entity_model",
            "id": 3311377648,
            "components": [
                {
                    "type": "ModelDefinitionComponent",
                    "name": "component_model_hexfire",
                    "filename": "data/hd/items/weapon/sword/hexfire/hexfire.model",
                    "visibleLayers": 1,
                    "lightMask": 19,
                    "shadowMask": 3,
                    "ghostShadows": false,
                    "floorModel": false,
                    "terrainBlendEnableYUpBlend": false,
                    "terrainBlendMode": 1
                }
            ]
        }
    ]
}