{
    "dependencies": {
        "particles": [],
        "models": [],
        "skeletons": [],
        "animations": [],
        "textures": [],
        "physics": [],
        "json": [],
        "variantdata": [],
        "objecteffects": [],
        "other": []
    },
    "type": "VariantTransformTable",
    "name": "VariantTransformTable",
    "entries": [
        {
            "type": "VariantColorTransform",
            "name": "cold",
            "transforms": [
                {
                    "type": "ColorTransform",
                    "name": "Red",
                    "colorAdjustment": {
                        "x": 0.0,
                        "y": 0.0,
                        "z": 0.0,
                        "w": 1.0
                    },
                    "hueAdjustment0": {
                        "x": 0.0,
                        "y": 0.0,
                        "z": 0.0,
                        "w": 0.0
                    },
                    "hueAdjustment1": {
                        "x": 0.0,
                        "y": 0.0,
                        "z": 0.0,
                        "w": 0.0
                    },
                    "satAdjustment0": {
                        "x": 0.0,
                        "y": 0.0,
                        "z": 0.0,
                        "w": 0.0
                    },
                    "satAdjustment1": {
                        "x": 0.0,
                        "y": 0.0,
                        "z": 0.0,
                        "w": 0.0
                    },
                    "colorTint": {
                        "x": 0.0,
                        "y": 0.0,
                        "z": 0.0,
                        "w": 0.0
                    }
                },
                {
                    "type": "ColorTransform",
                    "name": "Green",
                    "colorAdjustment": {
                        "x": 0.0,
                        "y": 0.0,
                        "z": 0.0,
                        "w": 1.0
                    },
                    "hueAdjustment0": {
                        "x": 0.0,
                        "y": 0.0,
                        "z": 0.0,
                        "w": 0.0
                    },
                    "hueAdjustment1": {
                        "x": 0.0,
                        "y": 0.0,
                        "z": 0.0,
                        "w": 0.0
                    },
                    "satAdjustment0": {
                        "x": 0.0,
                        "y": 0.0,
                        "z": 0.0,
                        "w": 0.0
                    },
                    "satAdjustment1": {
                        "x": 0.0,
                        "y": 0.0,
                        "z": 0.0,
                        "w": 0.0
                    },
                    "colorTint": {
                        "x": 0.0,
                        "y": 0.0,
                        "z": 0.0,
                        "w": 0.0
                    }
                },
                {
                    "type": "ColorTransform",
                    "name": "Blue",
                    "colorAdjustment": {
                        "x": 0.0,
                        "y": 0.0,
                        "z": 0.0,
                        "w": 1.0
                    },
                    "hueAdjustment0": {
                        "x": 0.0,
                        "y": 0.0,
                        "z": 0.0,
                        "w": 0.0
                    },
                    "hueAdjustment1": {
                        "x": 0.0,
                        "y": 0.0,
                        "z": 0.0,
                        "w": 0.0
                    },
                    "satAdjustment0": {
                        "x": 0.0,
                        "y": 0.0,
                        "z": 0.0,
                        "w": 0.0
                    },
                    "satAdjustment1": {
                        "x": 0.0,
                        "y": 0.0,
                        "z": 0.0,
                        "w": 0.0
                    },
                    "colorTint": {
                        "x": 0.0,
                        "y": 0.0,
                        "z": 0.0,
                        "w": 0.0
                    }
                }
            ]
        },
        {
            "type": "VariantColorTransform",
            "name": "poison",
            "transforms": [
                {
                    "type": "ColorTransform",
                    "name": "Red001",
                    "colorAdjustment": {
                        "x": 0.0,
                        "y": 0.0,
                        "z": 0.0,
                        "w": 1.0
                    },
                    "hueAdjustment0": {
                        "x": 0.0,
                        "y": 0.0,
                        "z": 0.0,
                        "w": 0.0
                    },
                    "hueAdjustment1": {
                        "x": 0.0,
                        "y": 0.0,
                        "z": 0.0,
                        "w": 0.0
                    },
                    "satAdjustment0": {
                        "x": 0.0,
                        "y": 0.0,
                        "z": 0.0,
                        "w": 0.0
                    },
                    "satAdjustment1": {
                        "x": 0.0,
                        "y": 0.0,
                        "z": 0.0,
                        "w": 0.0
                    },
                    "colorTint": {
                        "x": 0.0,
                        "y": 0.0,
                        "z": 0.0,
                        "w": 0.0
                    }
                },
                {
                    "type": "ColorTransform",
                    "name": "Green001",
                    "colorAdjustment": {
                        "x": 0.0,
                        "y": 0.0,
                        "z": 0.0,
                        "w": 1.0
                    },
                    "hueAdjustment0": {
                        "x": 0.0,
                        "y": 0.0,
                        "z": 0.0,
                        "w": 0.0
                    },
                    "hueAdjustment1": {
                        "x": 0.0,
                        "y": 0.0,
                        "z": 0.0,
                        "w": 0.0
                    },
                    "satAdjustment0": {
                        "x": 0.0,
                        "y": 0.0,
                        "z": 0.0,
                        "w": 0.0
                    },
                    "satAdjustment1": {
                        "x": 0.0,
                        "y": 0.0,
                        "z": 0.0,
                        "w": 0.0
                    },
                    "colorTint": {
                        "x": 0.0,
                        "y": 0.0,
                        "z": 0.0,
                        "w": 0.0
                    }
                },
                {
                    "type": "ColorTransform",
                    "name": "Blue001",
                    "colorAdjustment": {
                        "x": 0.0,
                        "y": 0.0,
                        "z": 0.0,
                        "w": 1.0
                    },
                    "hueAdjustment0": {
                        "x": 0.0,
                        "y": 0.0,
                        "z": 0.0,
                        "w": 0.0
                    },
                    "hueAdjustment1": {
                        "x": 0.0,
                        "y": 0.0,
                        "z": 0.0,
                        "w": 0.0
                    },
                    "satAdjustment0": {
                        "x": 0.0,
                        "y": 0.0,
                        "z": 0.0,
                        "w": 0.0
                    },
                    "satAdjustment1": {
                        "x": 0.0,
                        "y": 0.0,
                        "z": 0.0,
                        "w": 0.0
                    },
                    "colorTint": {
                        "x": 0.0,
                        "y": 0.0,
                        "z": 0.0,
                        "w": 0.0
                    }
                }
            ]
        },
        {
            "type": "VariantColorTransform",
            "name": "level0",
            "transforms": [
                {
                    "type": "ColorTransform",
                    "name": "Red002",
                    "colorAdjustment": {
                        "x": 0.0,
                        "y": 0.0,
                        "z": 0.0,
                        "w": 0.15
                    },
                    "hueAdjustment0": {
                        "x": 0.0,
                        "y": 0.0,
                        "z": 0.0,
                        "w": 0.0
                    },
                    "hueAdjustment1": {
                        "x": 0.0,
                        "y": 0.0,
                        "z": 0.0,
                        "w": 0.0
                    },
                    "satAdjustment0": {
                        "x": 0.0,
                        "y": 0.0,
                        "z": 0.0,
                        "w": 0.0
                    },
                    "satAdjustment1": {
                        "x": 0.0,
                        "y": 0.0,
                        "z": 0.0,
                        "w": 0.0
                    },
                    "colorTint": {
                        "x": 0.0,
                        "y": 0.0,
                        "z": 0.0,
                        "w": 0.0
                    }
                },
                {
                    "type": "ColorTransform",
                    "name": "Green002",
                    "colorAdjustment": {
                        "x": 0.0,
                        "y": 0.0,
                        "z": 0.0,
                        "w": 1.0
                    },
                    "hueAdjustment0": {
                        "x": 0.0,
                        "y": 0.0,
                        "z": 0.0,
                        "w": 0.0
                    },
                    "hueAdjustment1": {
                        "x": 0.0,
                        "y": 0.0,
                        "z": 0.0,
                        "w": 0.0
                    },
                    "satAdjustment0": {
                        "x": 0.0,
                        "y": 0.0,
                        "z": 0.0,
                        "w": 0.0
                    },
                    "satAdjustment1": {
                        "x": 0.0,
                        "y": 0.0,
                        "z": 0.0,
                        "w": 0.0
                    },
                    "colorTint": {
                        "x": 0.0,
                        "y": 0.0,
                        "z": 0.0,
                        "w": 0.0
                    }
                },
                {
                    "type": "ColorTransform",
                    "name": "Blue002",
                    "colorAdjustment": {
                        "x": 0.0,
                        "y": 0.0,
                        "z": 0.0,
                        "w": 1.0
                    },
                    "hueAdjustment0": {
                        "x": 0.0,
                        "y": 0.0,
                        "z": 0.0,
                        "w": 0.0
                    },
                    "hueAdjustment1": {
                        "x": 0.0,
                        "y": 0.0,
                        "z": 0.0,
                        "w": 0.0
                    },
                    "satAdjustment0": {
                        "x": 0.0,
                        "y": 0.0,
                        "z": 0.0,
                        "w": 0.0
                    },
                    "satAdjustment1": {
                        "x": 0.0,
                        "y": 0.0,
                        "z": 0.0,
                        "w": 0.0
                    },
                    "colorTint": {
                        "x": 0.0,
                        "y": 0.0,
                        "z": 0.0,
                        "w": 0.0
                    }
                }
            ]
        },
        {
            "type": "VariantColorTransform",
            "name": "level1",
            "transforms": [
                {
                    "type": "ColorTransform",
                    "name": "Red003",
                    "colorAdjustment": {
                        "x": 0.55,
                        "y": -0.07,
                        "z": -0.01,
                        "w": 1.0
                    },
                    "hueAdjustment0": {
                        "x": 0.0,
                        "y": 0.0,
                        "z": 0.0,
                        "w": 0.0
                    },
                    "hueAdjustment1": {
                        "x": 0.0,
                        "y": 0.0,
                        "z": 0.0,
                        "w": 0.0
                    },
                    "satAdjustment0": {
                        "x": 0.0,
                        "y": 0.0,
                        "z": 0.0,
                        "w": 0.0
                    },
                    "satAdjustment1": {
                        "x": 0.0,
                        "y": 0.0,
                        "z": 0.0,
                        "w": 0.0
                    },
                    "colorTint": {
                        "x": 0.0,
                        "y": 0.0,
                        "z": 0.0,
                        "w": 0.0
                    }
                },
                {
                    "type": "ColorTransform",
                    "name": "Green003",
                    "colorAdjustment": {
                        "x": 0.57,
                        "y": -0.01,
                        "z": 0.65,
                        "w": 1.0
                    },
                    "hueAdjustment0": {
                        "x": 0.0,
                        "y": 0.0,
                        "z": 0.0,
                        "w": 0.0
                    },
                    "hueAdjustment1": {
                        "x": 0.0,
                        "y": 0.0,
                        "z": 0.0,
                        "w": 0.0
                    },
                    "satAdjustment0": {
                        "x": 0.0,
                        "y": 0.0,
                        "z": 0.0,
                        "w": 0.0
                    },
                    "satAdjustment1": {
                        "x": 0.0,
                        "y": 0.0,
                        "z": 0.0,
                        "w": 0.0
                    },
                    "colorTint": {
                        "x": 0.0,
                        "y": 0.0,
                        "z": 0.0,
                        "w": 0.0
                    }
                },
                {
                    "type": "ColorTransform",
                    "name": "Blue003",
                    "colorAdjustment": {
                        "x": 0.47,
                        "y": 0.0,
                        "z": -0.11,
                        "w": 1.0
                    },
                    "hueAdjustment0": {
                        "x": 0.0,
                        "y": 0.0,
                        "z": 0.0,
                        "w": 0.0
                    },
                    "hueAdjustment1": {
                        "x": 0.0,
                        "y": 0.0,
                        "z": 0.0,
                        "w": 0.0
                    },
                    "satAdjustment0": {
                        "x": 0.0,
                        "y": 0.0,
                        "z": 0.0,
                        "w": 0.0
                    },
                    "satAdjustment1": {
                        "x": 0.0,
                        "y": 0.0,
                        "z": 0.0,
                        "w": 0.0
                    },
                    "colorTint": {
                        "x": 0.0,
                        "y": 0.0,
                        "z": 0.0,
                        "w": 0.0
                    }
                }
            ]
        },
        {
            "type": "VariantColorTransform",
            "name": "level2",
            "transforms": [
                {
                    "type": "ColorTransform",
                    "name": "Red004",
                    "colorAdjustment": {
                        "x": 0.24,
                        "y": -0.1,
                        "z": -0.33,
                        "w": 1.0
                    },
                    "hueAdjustment0": {
                        "x": 0.0,
                        "y": 0.0,
                        "z": 0.0,
                        "w": 0.0
                    },
                    "hueAdjustment1": {
                        "x": 0.0,
                        "y": 0.0,
                        "z": 0.0,
                        "w": 0.0
                    },
                    "satAdjustment0": {
                        "x": 0.0,
                        "y": 0.0,
                        "z": 0.0,
                        "w": 0.0
                    },
                    "satAdjustment1": {
                        "x": 0.0,
                        "y": 0.0,
                        "z": 0.0,
                        "w": 0.0
                    },
                    "colorTint": {
                        "x": 0.0,
                        "y": 0.0,
                        "z": 0.0,
                        "w": 0.0
                    }
                },
                {
                    "type": "ColorTransform",
                    "name": "Green004",
                    "colorAdjustment": {
                        "x": 0.28,
                        "y": -0.07,
                        "z": -0.53,
                        "w": 1.0
                    },
                    "hueAdjustment0": {
                        "x": 0.0,
                        "y": 0.0,
                        "z": 0.0,
                        "w": 0.0
                    },
                    "hueAdjustment1": {
                        "x": 0.0,
                        "y": 0.0,
                        "z": 0.0,
                        "w": 0.0
                    },
                    "satAdjustment0": {
                        "x": 0.0,
                        "y": 0.0,
                        "z": 0.0,
                        "w": 0.0
                    },
                    "satAdjustment1": {
                        "x": 0.0,
                        "y": 0.0,
                        "z": 0.0,
                        "w": 0.0
                    },
                    "colorTint": {
                        "x": 0.0,
                        "y": 0.0,
                        "z": 0.0,
                        "w": 0.0
                    }
                },
                {
                    "type": "ColorTransform",
                    "name": "Blue004",
                    "colorAdjustment": {
                        "x": 0.37,
                        "y": 0.6,
                        "z": -0.56,
                        "w": 1.0
                    },
                    "hueAdjustment0": {
                        "x": 0.0,
                        "y": 0.0,
                        "z": 0.0,
                        "w": 0.0
                    },
                    "hueAdjustment1": {
                        "x": 0.0,
                        "y": 0.0,
                        "z": 0.0,
                        "w": 0.0
                    },
                    "satAdjustment0": {
                        "x": 0.0,
                        "y": 0.0,
                        "z": 0.0,
                        "w": 0.0
                    },
                    "satAdjustment1": {
                        "x": 0.0,
                        "y": 0.0,
                        "z": 0.0,
                        "w": 0.0
                    },
                    "colorTint": {
                        "x": 0.0,
                        "y": 0.0,
                        "z": 0.0,
                        "w": 0.0
                    }
                }
            ]
        },
        {
            "type": "VariantColorTransform",
            "name": "level3",
            "transforms": [
                {
                    "type": "ColorTransform",
                    "name": "Red005",
                    "colorAdjustment": {
                        "x": 0.05,
                        "y": -0.07,
                        "z": 0.0,
                        "w": 1.0
                    },
                    "hueAdjustment0": {
                        "x": 0.0,
                        "y": 0.0,
                        "z": 0.0,
                        "w": 0.0
                    },
                    "hueAdjustment1": {
                        "x": 0.0,
                        "y": 0.0,
                        "z": 0.0,
                        "w": 0.0
                    },
                    "satAdjustment0": {
                        "x": 0.0,
                        "y": 0.0,
                        "z": 0.0,
                        "w": 0.0
                    },
                    "satAdjustment1": {
                        "x": 0.0,
                        "y": 0.0,
                        "z": 0.0,
                        "w": 0.0
                    },
                    "colorTint": {
                        "x": 0.0,
                        "y": 0.0,
                        "z": 0.0,
                        "w": 0.0
                    }
                },
                {
                    "type": "ColorTransform",
                    "name": "Green005",
                    "colorAdjustment": {
                        "x": 0.14,
                        "y": 0.0,
                        "z": 0.0,
                        "w": 1.0
                    },
                    "hueAdjustment0": {
                        "x": 0.0,
                        "y": 0.0,
                        "z": 0.0,
                        "w": 0.0
                    },
                    "hueAdjustment1": {
                        "x": 0.0,
                        "y": 0.0,
                        "z": 0.0,
                        "w": 0.0
                    },
                    "satAdjustment0": {
                        "x": 0.0,
                        "y": 0.0,
                        "z": 0.0,
                        "w": 0.0
                    },
                    "satAdjustment1": {
                        "x": 0.0,
                        "y": 0.0,
                        "z": 0.0,
                        "w": 0.0
                    },
                    "colorTint": {
                        "x": 0.0,
                        "y": 0.0,
                        "z": 0.0,
                        "w": 0.0
                    }
                },
                {
                    "type": "ColorTransform",
                    "name": "Blue005",
                    "colorAdjustment": {
                        "x": 0.1,
                        "y": 0.2,
                        "z": 0.0,
                        "w": 1.0
                    },
                    "hueAdjustment0": {
                        "x": 0.0,
                        "y": 0.0,
                        "z": 0.0,
                        "w": 0.0
                    },
                    "hueAdjustment1": {
                        "x": 0.0,
                        "y": 0.0,
                        "z": 0.0,
                        "w": 0.0
                    },
                    "satAdjustment0": {
                        "x": 0.0,
                        "y": 0.0,
                        "z": 0.0,
                        "w": 0.0
                    },
                    "satAdjustment1": {
                        "x": 0.0,
                        "y": 0.0,
                        "z": 0.0,
                        "w": 0.0
                    },
                    "colorTint": {
                        "x": 0.0,
                        "y": 0.0,
                        "z": 0.0,
                        "w": 0.0
                    }
                }
            ]
        },
        {
            "type": "VariantColorTransform",
            "name": "level4",
            "transforms": [
                {
                    "type": "ColorTransform",
                    "name": "Red006",
                    "colorAdjustment": {
                        "x": 0.61,
                        "y": -0.39,
                        "z": -0.62,
                        "w": 1.0
                    },
                    "hueAdjustment0": {
                        "x": 0.0,
                        "y": 0.0,
                        "z": 0.0,
                        "w": 0.0
                    },
                    "hueAdjustment1": {
                        "x": 0.0,
                        "y": 0.0,
                        "z": 0.0,
                        "w": 0.0
                    },
                    "satAdjustment0": {
                        "x": 0.0,
                        "y": 0.0,
                        "z": 0.0,
                        "w": 0.0
                    },
                    "satAdjustment1": {
                        "x": 0.0,
                        "y": 0.0,
                        "z": 0.0,
                        "w": 0.0
                    },
                    "colorTint": {
                        "x": 0.0,
                        "y": 0.0,
                        "z": 0.0,
                        "w": 0.0
                    }
                },
                {
                    "type": "ColorTransform",
                    "name": "Green006",
                    "colorAdjustment": {
                        "x": 0.0,
                        "y": 0.0,
                        "z": 0.0,
                        "w": 0.1
                    },
                    "hueAdjustment0": {
                        "x": 0.0,
                        "y": 0.0,
                        "z": 0.0,
                        "w": 0.0
                    },
                    "hueAdjustment1": {
                        "x": 0.0,
                        "y": 0.0,
                        "z": 0.0,
                        "w": 0.0
                    },
                    "satAdjustment0": {
                        "x": 0.0,
                        "y": 0.0,
                        "z": 0.0,
                        "w": 0.0
                    },
                    "satAdjustment1": {
                        "x": 0.0,
                        "y": 0.0,
                        "z": 0.0,
                        "w": 0.0
                    },
                    "colorTint": {
                        "x": 0.07843138,
                        "y": 0.07843138,
                        "z": 0.07843138,
                        "w": 1.0
                    }
                },
                {
                    "type": "ColorTransform",
                    "name": "Blue006",
                    "colorAdjustment": {
                        "x": 0.06,
                        "y": -0.32,
                        "z": -0.41,
                        "w": 1.0
                    },
                    "hueAdjustment0": {
                        "x": 0.0,
                        "y": 0.0,
                        "z": 0.0,
                        "w": 0.0
                    },
                    "hueAdjustment1": {
                        "x": 0.0,
                        "y": 0.0,
                        "z": 0.0,
                        "w": 0.0
                    },
                    "satAdjustment0": {
                        "x": 0.0,
                        "y": 0.0,
                        "z": 0.0,
                        "w": 0.0
                    },
                    "satAdjustment1": {
                        "x": 0.0,
                        "y": 0.0,
                        "z": 0.0,
                        "w": 0.0
                    },
                    "colorTint": {
                        "x": 0.0,
                        "y": 0.0,
                        "z": 0.0,
                        "w": 0.0
                    }
                }
            ]
        },
        {
            "type": "VariantColorTransform",
            "name": "misc",
            "transforms": [
                {
                    "type": "ColorTransform",
                    "name": "Red007",
                    "colorAdjustment": {
                        "x": 0.0,
                        "y": 0.0,
                        "z": 0.0,
                        "w": 1.0
                    },
                    "hueAdjustment0": {
                        "x": 0.0,
                        "y": 0.0,
                        "z": 0.0,
                        "w": 0.0
                    },
                    "hueAdjustment1": {
                        "x": 0.0,
                        "y": 0.0,
                        "z": 0.0,
                        "w": 0.0
                    },
                    "satAdjustment0": {
                        "x": 0.0,
                        "y": 0.0,
                        "z": 0.0,
                        "w": 0.0
                    },
                    "satAdjustment1": {
                        "x": 0.0,
                        "y": 0.0,
                        "z": 0.0,
                        "w": 0.0
                    },
                    "colorTint": {
                        "x": 0.0,
                        "y": 0.0,
                        "z": 0.0,
                        "w": 0.0
                    }
                },
                {
                    "type": "ColorTransform",
                    "name": "Green007",
                    "colorAdjustment": {
                        "x": 0.0,
                        "y": 0.0,
                        "z": 0.0,
                        "w": 1.0
                    },
                    "hueAdjustment0": {
                        "x": 0.0,
                        "y": 0.0,
                        "z": 0.0,
                        "w": 0.0
                    },
                    "hueAdjustment1": {
                        "x": 0.0,
                        "y": 0.0,
                        "z": 0.0,
                        "w": 0.0
                    },
                    "satAdjustment0": {
                        "x": 0.0,
                        "y": 0.0,
                        "z": 0.0,
                        "w": 0.0
                    },
                    "satAdjustment1": {
                        "x": 0.0,
                        "y": 0.0,
                        "z": 0.0,
                        "w": 0.0
                    },
                    "colorTint": {
                        "x": 0.0,
                        "y": 0.0,
                        "z": 0.0,
                        "w": 0.0
                    }
                },
                {
                    "type": "ColorTransform",
                    "name": "Blue007",
                    "colorAdjustment": {
                        "x": 0.0,
                        "y": 0.0,
                        "z": 0.0,
                        "w": 1.0
                    },
                    "hueAdjustment0": {
                        "x": 0.0,
                        "y": 0.0,
                        "z": 0.0,
                        "w": 0.0
                    },
                    "hueAdjustment1": {
                        "x": 0.0,
                        "y": 0.0,
                        "z": 0.0,
                        "w": 0.0
                    },
                    "satAdjustment0": {
                        "x": 0.0,
                        "y": 0.0,
                        "z": 0.0,
                        "w": 0.0
                    },
                    "satAdjustment1": {
                        "x": 0.0,
                        "y": 0.0,
                        "z": 0.0,
                        "w": 0.0
                    },
                    "colorTint": {
                        "x": 0.0,
                        "y": 0.0,
                        "z": 0.0,
                        "w": 0.0
                    }
                }
            ]
        }
    ]
}